{"yichengnainai": "\u4e00\u8bda\u5976\u5976", "sifu": "\u79c1\u670d", "yichengzongsi": "\u4e00\u8bda\u603b\u53f8", "dongzhifu": "\u51ac\u5236\u670d", "xiazhifu": "\u590f\u5236\u670d", "xiasifu": "\u590f\u79c1\u670d", "shuizhe": "\u6c34\u7740", "wanyehua": "\u4e07\u591c\u82b1", "wunvfu": "\u5deb\u5973\u670d", "qiandong": "\u5343\u51ac", "dongsifu": "\u51ac\u79c1\u670d", "qianchuanlaoshi": "\u5343\u5ddd\u8001\u5e08", "zhifu": "\u5236\u670d", "qianbo": "\u5343\u6ce2", "qianbojie": "\u5343\u6ce2\u59d0", "youjia": "\u53cb\u52a0", "ticaofu": "\u4f53\u64cd\u670d", "shenghuyuan": "\u5723\u62a4\u9662", "yanjiufu": "\u7814\u7a76\u670d", "tianshixifeier": "\u5929\u4f7f\u5e0c\u83f2\u5c14", "yaojingzhuang": "\u5996\u7cbe\u88c5", "tianshilian": "\u5929\u4f7f\u83b2", "sishenzhuang": "\u6b7b\u795e\u88c5", "tianshileiya": "\u5929\u4f7f\u96f7\u4e9a", "sishenliandao": "\u6b7b\u795e\u9570\u5200", "xueshenghuizhang": "\u5b66\u751f\u4f1a\u957f", "xiaotao": "\u5c0f\u6843", "hushi": "\u62a4\u58eb", "rixianglian": "\u65e5\u5411\u601c", "nvpuzhuang": "\u5973\u4ec6\u88c5", "meng": "\u68a6", "shuiyi": "\u7761\u8863", "shuizhilai": "\u6c34\u4e4b\u6fd1", "dongzhifupeidao": "\u51ac\u5236\u670d\u4f69\u5200", "dongsifupeidao": "\u51ac\u79c1\u670d\u4f69\u5200", "aiyi": "\u7231\u8863", "liuli": "\u7409\u7483", "yuzhoufu": "\u5b87\u5b99\u670d", "baiyu": "\u767d\u7fbd", "shenyedahe": "\u795e\u91ce\u5927\u548c", "lihuaxi": "\u7acb\u82b1\u5e0c", "xiangzimuqin": "\u7fd4\u5b50\u6bcd\u4eb2", "tengyuantong": "\u85e4\u539f\u77b3", "alu": "\u963f\u9732", "changtai": "\u5e38\u6001", "qingmuxiangzi": "\u9752\u6728\u7fd4\u5b50", "qingmulingyin": "\u9752\u6728\u94c3\u97f3"}